drosolf/Hallem_Carlson_2006.csv
drosolf/__init__.py
drosolf/kcs.py
drosolf/orns.py
drosolf/pns.py
drosolf-0.1.3.dist-info/LICENSE.txt
drosolf-0.1.3.dist-info/METADATA
drosolf-0.1.3.dist-info/WHEEL
drosolf-0.1.3.dist-info/top_level.txt
drosolf-0.1.3.dist-info/RECORD
