Metadata-Version: 2.1
Name: drosolf
Version: 0.1.3
Summary: Responses of 1st , 2nd, and soon 3rd order Drosophila olfactory neurons
Home-page: https://github.com/tom-f-oconnell/drosolf
Author: Tom O'Connell
Author-email: toconnel@caltech.edu
License: GPLv3
Keywords: neuroscience olfaction population coding drosophila
Platform: UNKNOWN
Requires-Dist: numpy
Requires-Dist: pandas
